f1_mcp_server/__init__.py
f1_mcp_server/__main__.py
f1_mcp_server/f1_data.py
f1_mcp_server/server.py
f1_mcp_server-0.1.0.dist-info/METADATA
f1_mcp_server-0.1.0.dist-info/WHEEL
f1_mcp_server-0.1.0.dist-info/entry_points.txt
f1_mcp_server-0.1.0.dist-info/licenses/LICENSE
f1_mcp_server-0.1.0.dist-info/RECORD
