Metadata-Version: 2.4
Name: f1-mcp-server
Version: 0.1.0
Summary: A Model Context Protocol (MCP) server that provides Formula One racing data for AI applications, including event schedules, driver information, telemetry data, race results, and performance analysis.
Project-URL: Homepage, https://www.machinetomachine.ai/
Project-URL: Repository, https://github.com/Machine-To-Machine/f1-mcp-server.git
Project-URL: Issues, https://github.com/Machine-To-Machine/f1-mcp-server/issues
Project-URL: Documentation, https://github.com/Machine-To-Machine/f1-mcp-server/blob/main/README.md
Project-URL: Changelog, https://github.com/Machine-To-Machine/f1-mcp-server/blob/main/CHANGELOG.md
Project-URL: Source Code, https://github.com/Machine-To-Machine/f1-mcp-server
Author: Machine-To-Machine
Maintainer-email: Will Pak <will@machinetomachine.ai>, "Harold Bott Jr." <harold@machinetomachine.ai>
License: MIT
License-File: LICENSE
Keywords: f1,fastf1,formula1,m2m,mcp,motorsport
Classifier: Development Status :: 4 - Beta
Classifier: Intended Audience :: Developers
Classifier: License :: OSI Approved :: MIT License
Classifier: Programming Language :: Python :: 3
Classifier: Programming Language :: Python :: 3.10
Classifier: Programming Language :: Python :: 3.11
Classifier: Programming Language :: Python :: 3.12
Classifier: Programming Language :: Python :: 3.13
Requires-Python: >=3.10
Requires-Dist: anyio>=4.9.0
Requires-Dist: click>=8.1.8
Requires-Dist: fastf1>=3.5.3
Requires-Dist: mcp>=1.6.0
Requires-Dist: numpy>=2.2.4
Requires-Dist: pandas>=2.2.3
Requires-Dist: uvicorn>=0.34.0
